{
    "1": {"item": "Thread", "count": 20},
    "2": {"item": "Identity Training Ticket IV", "count": 5},
    "3": {"item": "Season 6 Uptie & Threadspinning only Shard (Universal)", "count": 5},
    "4": {"item": "Identity Training Ticket IV", "count": 4},
    "5": {"item": "Extraction Ticket", "count": 1},
    "6": {"item": "Thread", "count": 20},
    "7": {"item": "Identity Training Ticket IV", "count": 5},
    "8": {"item": "Thread", "count": 20},
    "9": {"item": "Season 6 Uptie & Threadspinning only Shard (Universal)", "count": 5},
    "10": {"item": "Extraction Ticket", "count": 1}, 
    "11": {"item": "Thread", "count": 20},
    "12": {"item": "Identity Training Ticket IV", "count": 5},
    "13": {"item": "Thread", "count": 20},
    "14": {"item": "Season 6 Uptie & Threadspinning only Shard (Universal)", "count": 5},
    "15": {"item": "Extraction Ticket", "count": 1},
    "16": {"item": "Thread", "count": 20},
    "17": {"item": "Identity Training Ticket IV", "count": 5},
    "18": {"item": "Thread", "count": 20},
    "19": {"item": "Identity Training Ticket IV", "count": 4},
    "20": {"item": "Extraction Ticket", "count": 1}, 
    "21": {"item": "Thread", "count": 20},
    "22": {"item": "Season 6 Uptie & Threadspinning only Shard (Universal)", "count": 5},
    "23": {"item": "Identity Training Ticket IV", "count": 4},
    "24": {"item": "Thread", "count": 20},
    "25": {"item": "Extraction Ticket", "count": 1},
    "26": {"item": "Identity Training Ticket IV", "count": 4},
    "27": {"item": "Thread", "count": 20},
    "28": {"item": "Season 6 Uptie & Threadspinning only Shard (Universal)", "count": 5},
    "29": {"item": "Thread", "count": 20},
    "30": {"item": "Extraction Ticket", "count": 1}, 
    "31": {"item": "Identity Training Ticket IV", "count": 4},
    "32": {"item": "Thread", "count": 20},
    "33": {"item": "Season 6 Uptie & Threadspinning only Shard (Universal)", "count": 5},
    "34": {"item": "Thread", "count": 20},
    "35": {"item": "Extraction Ticket", "count": 1},
    "36": {"item": "Identity Training Ticket IV", "count": 4},
    "37": {"item": "Thread", "count": 20},
    "38": {"item": "Season 6 Uptie & Threadspinning only Shard (Universal)", "count": 5},
    "39": {"item": "Thread", "count": 20},
    "40": {"item": "Decaextraction Ticket", "count": 1},
    "41": {"item": "Identity Training Ticket IV", "count": 4},
    "42": {"item": "Thread", "count": 20},
    "43": {"item": "Identity Training Ticket IV", "count": 4},
    "44": {"item": "Thread", "count": 20},
    "45": {"item": "Extraction Ticket", "count": 1},
    "46": {"item": "Identity Training Ticket IV", "count": 4},
    "47": {"item": "Thread", "count": 20},
    "48": {"item": "Season 6 Uptie & Threadspinning only Shard (Universal)", "count": 5},
    "49": {"item": "Thread", "count": 20},
    "50": {"item": "Season 6: Mirror of Immortality Commemorative Banner", "count": 1},
    "51": {"item": "Season 6 Uptie & Threadspinning only Shard (Universal)", "count": 5},
    "52": {"item": "Thread", "count": 20},
    "53": {"item": "Identity Training Ticket IV", "count": 4},
    "54": {"item": "Season 6 Uptie & Threadspinning only Shard (Universal)", "count": 5},
    "55": {"item": "Extraction Ticket", "count": 1}
}